{
  "folders": [
    {
      "id": 1,
      "name": "HongAnh"
    },
    {
      "id": 2,
      "name": "New one"
    },
    {
      "id": 3,
      "name": "123"
    },
    {
      "id": 4,
      "name": "Yolo"
    },
    {
      "id": 5,
      "name": "WhatIf"
    },
    {
      "id": 6,
      "name": "Jennie"
    },
    {
      "name": "Test",
      "id": 7
    },
    {
      "name": "Check1",
      "id": 8
    },
    {
      "name": "Hello World",
      "id": 9
    },
    {
      "name": "123",
      "id": 10
    },
    {
      "name": "123",
      "id": 11
    },
    {
      "name": "123",
      "id": 12
    }
  ]
}